{"global":{"name":"Tero","uid":2297370779,"avatar":"","platform":"PC","level":43,"toNextLevelPercent":77,"internalUpdateCount":14411,"bans":{"isActive":false,"remainingSeconds":0,"last_banReason":"COMPETITIVE_DODGE_COOLDOWN"},"rank":{"rankScore":6362,"rankName":"Gold","rankDiv":3,"ladderPosPlatform":-1,"rankImg":"https://api.mozambiquehe.re/assets/ranks/gold3.png","rankedSeason":"season14_split_2"},"arena":{"rankScore":2361,"rankName":"Silver","rankDiv":3,"ladderPosPlatform":-1,"rankImg":"https://api.mozambiquehe.re/assets/ranks/silver3.png","rankedSeason":"arenas14_split_2"},"battlepass":{"level":"-1","history":{"season1":-1,"season2":-1,"season3":-1,"season4":-1,"season5":-1,"season6":-1,"season7":-1,"season8":111,"season9":111,"season10":111,"season11":111,"season12":111,"season13":-1,"season14":0}},"internalParsingVersion":2,"badges":[{"name":"You're Tiering Me Apart: Ranked Season 11","value":9},{"name":"You're Tiering Me Apart: Arenas Ranked Season 10","value":8},{"name":"Team. Work.","value":0},{"name":"Pack Victory","value":0},{"name":"No Witnesses","value":0},{"name":"Long Shot","value":0},{"name":"Impress Me","value":10},{"name":"Genesis Juggernaut","value":0},{"name":"Fully Kitted","value":0},{"name":"April Fools","value":0}],"levelPrestige":1},"realtime":{"lobbyState":"open","isOnline":0,"isInGame":0,"canJoin":0,"partyFull":0,"selectedLegend":"Bloodhound","currentState":"offline","currentStateSinceTimestamp":-1,"currentStateAsText":"Offline"},"legends":{"selected":{"LegendName":"Bloodhound","data":[{"name":"BR Kills","value":313,"key":"specialEvent_kills","global":false},{"name":"Eye: Enemies scanned","value":2345,"key":"enemies_scanned","global":false},{"name":"BR Damage","value":125060,"key":"damage","global":false}],"gameInfo":{"skin":"Feral's Future","skinRarity":"Legendary","frame":"Legend of the West","frameRarity":"Legendary","pose":"Unbreakable Bond","poseRarity":"Epic","intro":"The true test","introRarity":"Common","badges":[{"name":"Account Level","value":544,"category":"Account Badges"},{"name":"Hot Streak","value":0,"category":"Bloodhound"},{"name":"Team. Work.","value":0,"category":"Account Badges"}]},"ImgAssets":{"icon":"https://api.mozambiquehe.re/assets/icons/bloodhound.png","banner":"https://api.mozambiquehe.re/assets/banners/bloodhound.jpg"}},"all":{"Global":{"ImgAssets":{"icon":"https://api.mozambiquehe.re/assets/icons/global.png","banner":"https://api.mozambiquehe.re/assets/banners/global.jpg"}},"Revenant":{"data":[{"name":"BR Damage","value":253743,"key":"damage","rank":{"rankPos":72927,"topPercent":11.87},"rankPlatformSpecific":{"rankPos":10976,"topPercent":13.18}},{"name":"Silence: Silenced knockdowns","value":131,"key":"silenced_targets_kills","rank":{"rankPos":27446,"topPercent":25.38},"rankPlatformSpecific":{"rankPos":"NOT_CALCULATED_YET","topPercent":"NOT_CALCULATED_YET"}},{"name":"Silence: Enemies silenced","value":853,"key":"silenced_targets","rank":{"rankPos":69999,"topPercent":17.97},"rankPlatformSpecific":{"rankPos":13254,"topPercent":20.93}},{"name":"BR Kills","value":577,"key":"specialEvent_kills","rank":{"rankPos":87168,"topPercent":15.58},"rankPlatformSpecific":{"rankPos":12215,"topPercent":16.42}},{"name":"BR Season 10 kills","value":52,"key":"kills_season_10","rank":{"rankPos":19250,"topPercent":27.94},"rankPlatformSpecific":{"rankPos":"NOT_CALCULATED_YET","topPercent":"NOT_CALCULATED_YET"}},{"name":"BR Season 10 wins","value":4,"key":"wins_season_10","rank":{"rankPos":14309,"topPercent":19.79},"rankPlatformSpecific":{"rankPos":"NOT_CALCULATED_YET","topPercent":"NOT_CALCULATED_YET"}}],"gameInfo":{"badges":[{"name":"Apex Predator","value":0},{"name":"Revenant's Wrath","value":4}]},"ImgAssets":{"icon":"https://api.mozambiquehe.re/assets/icons/revenant.png","banner":"https://api.mozambiquehe.re/assets/banners/revenant.jpg"}},"Crypto":{"data":[{"name":"BR Kills","value":20,"key":"kills","rank":{"rankPos":794794,"topPercent":63.56},"rankPlatformSpecific":{"rankPos":78980,"topPercent":67.34}},{"name":"Neurolink: Enemies scanned","value":63,"key":"passive_enemies_scanned","rank":{"rankPos":107133,"topPercent":85.56},"rankPlatformSpecific":{"rankPos":"NOT_CALCULATED_YET","topPercent":"NOT_CALCULATED_YET"}},{"name":"BR Kills","value":26,"key":"specialEvent_kills","rank":{"rankPos":348777,"topPercent":83.47},"rankPlatformSpecific":{"rankPos":35254,"topPercent":86.54}},{"name":"BR Damage","value":13390,"key":"specialEvent_damage","rank":{"rankPos":355353,"topPercent":79.89},"rankPlatformSpecific":{"rankPos":36826,"topPercent":84.73}},{"name":"BR Wins","value":3,"key":"specialEvent_wins","rank":{"rankPos":181697,"topPercent":70.1},"rankPlatformSpecific":{"rankPos":18653,"topPercent":71.35}}],"ImgAssets":{"icon":"https://api.mozambiquehe.re/assets/icons/crypto.png","banner":"https://api.mozambiquehe.re/assets/banners/crypto.jpg"}},"Horizon":{"data":[{"name":"BR Kills","value":35,"key":"kills","rank":{"rankPos":1873298,"topPercent":74.59},"rankPlatformSpecific":{"rankPos":471637,"topPercent":82.66}},{"name":"BR Damage","value":14395,"key":"damage","rank":{"rankPos":1074256,"topPercent":85.85},"rankPlatformSpecific":{"rankPos":272513,"topPercent":91.75}},{"name":"BR Season 8 wins","value":0,"key":"wins_season_8","rank":{"rankPos":80719,"topPercent":87.71},"rankPlatformSpecific":{"rankPos":12746,"topPercent":89.67}}],"ImgAssets":{"icon":"https://api.mozambiquehe.re/assets/icons/horizon.png","banner":"https://api.mozambiquehe.re/assets/banners/horizon.jpg"}},"Gibraltar":{"data":[{"name":"BR Kills","value":752,"key":"kills","rank":{"rankPos":116075,"topPercent":4.98},"rankPlatformSpecific":{"rankPos":10048,"topPercent":3.74}},{"name":"BR Damage","value":362852,"key":"damage","rank":{"rankPos":57947,"topPercent":8.76},"rankPlatformSpecific":{"rankPos":5822,"topPercent":11.14}},{"name":"BR Revives","value":130,"key":"revives","rank":{"rankPos":6548,"topPercent":16.38},"rankPlatformSpecific":{"rankPos":"NOT_CALCULATED_YET","topPercent":"NOT_CALCULATED_YET"}},{"name":"Bombardment: Kills","value":14,"key":"bombardment_kills","rank":{"rankPos":19335,"topPercent":19.8},"rankPlatformSpecific":{"rankPos":"NOT_CALCULATED_YET","topPercent":"NOT_CALCULATED_YET"}},{"name":"BR Season 7 kills","value":10,"key":"kills_season_7","rank":{"rankPos":38454,"topPercent":35.78},"rankPlatformSpecific":{"rankPos":"NOT_CALCULATED_YET","topPercent":"NOT_CALCULATED_YET"}},{"name":"BR Season 7 wins","value":2,"key":"wins_season_7","rank":{"rankPos":12991,"topPercent":28.2},"rankPlatformSpecific":{"rankPos":"NOT_CALCULATED_YET","topPercent":"NOT_CALCULATED_YET"}},{"name":"BR Kills","value":830,"key":"specialEvent_kills","rank":{"rankPos":70223,"topPercent":12.38},"rankPlatformSpecific":{"rankPos":5925,"topPercent":14.47}},{"name":"BR Damage","value":400094,"key":"specialEvent_damage","rank":{"rankPos":46179,"topPercent":9.45},"rankPlatformSpecific":{"rankPos":4721,"topPercent":13.23}},{"name":"BR Wins","value":81,"key":"specialEvent_wins","rank":{"rankPos":28102,"topPercent":7.54},"rankPlatformSpecific":{"rankPos":3367,"topPercent":10.01}},{"name":"BR Season 9 wins","value":29,"key":"wins_season_9","rank":{"rankPos":1606,"topPercent":2.35},"rankPlatformSpecific":{"rankPos":566,"topPercent":11.59}},{"name":"BR Season 10 kills","value":106,"key":"kills_season_10","rank":{"rankPos":7520,"topPercent":9.16},"rankPlatformSpecific":{"rankPos":"NOT_CALCULATED_YET","topPercent":"NOT_CALCULATED_YET"}},{"name":"BR Season 10 wins","value":12,"key":"wins_season_10","rank":{"rankPos":3646,"topPercent":4.32},"rankPlatformSpecific":{"rankPos":1804,"topPercent":28}},{"name":"BR Season 11 kills","value":174,"key":"kills_season_11","rank":{"rankPos":4934,"topPercent":5.1},"rankPlatformSpecific":{"rankPos":"NOT_CALCULATED_YET","topPercent":"NOT_CALCULATED_YET"}},{"name":"BR Season 11 wins","value":14,"key":"wins_season_11","rank":{"rankPos":2893,"topPercent":2.97},"rankPlatformSpecific":{"rankPos":1353,"topPercent":14.93}},{"name":"BR Season 12 wins","value":8,"key":"wins_season_12","rank":{"rankPos":5380,"topPercent":12.34},"rankPlatformSpecific":{"rankPos":"NOT_CALCULATED_YET","topPercent":"NOT_CALCULATED_YET"}},{"name":"BR Season 12 kills","value":99,"key":"kills_season_12","rank":{"rankPos":8159,"topPercent":17.34},"rankPlatformSpecific":{"rankPos":"NOT_CALCULATED_YET","topPercent":"NOT_CALCULATED_YET"}}],"gameInfo":{"badges":[{"name":"Apex Gibraltar","value":5},{"name":"Gibraltar's Wrath","value":0},{"name":"Double Duty","value":0}]},"ImgAssets":{"icon":"https://api.mozambiquehe.re/assets/icons/gibraltar.png","banner":"https://api.mozambiquehe.re/assets/banners/gibraltar.jpg"}},"Wattson":{"data":[{"name":"BR Kills","value":7,"key":"kills","rank":{"rankPos":925478,"topPercent":60.98},"rankPlatformSpecific":{"rankPos":"NOT_CALCULATED_YET","topPercent":"NOT_CALCULATED_YET"}},{"name":"BR Winning kills","value":0,"key":"winning_kills","rank":{"rankPos":7578,"topPercent":74.03},"rankPlatformSpecific":{"rankPos":"NOT_CALCULATED_YET","topPercent":"NOT_CALCULATED_YET"}},{"name":"BR Kills","value":24,"key":"specialEvent_kills","rank":{"rankPos":493254,"topPercent":82.57},"rankPlatformSpecific":{"rankPos":"NOT_CALCULATED_YET","topPercent":"NOT_CALCULATED_YET"}},{"name":"BR Damage","value":13986,"key":"specialEvent_damage","rank":{"rankPos":424833,"topPercent":76.76},"rankPlatformSpecific":{"rankPos":"NOT_CALCULATED_YET","topPercent":"NOT_CALCULATED_YET"}},{"name":"BR Wins","value":4,"key":"specialEvent_wins","rank":{"rankPos":259605,"topPercent":62.93},"rankPlatformSpecific":{"rankPos":"NOT_CALCULATED_YET","topPercent":"NOT_CALCULATED_YET"}},{"name":"BR Marksman kills","value":0,"key":"marksman_kills","rank":{"rankPos":1558,"topPercent":65.16},"rankPlatformSpecific":{"rankPos":763,"topPercent":48.88}}],"ImgAssets":{"icon":"https://api.mozambiquehe.re/assets/icons/wattson.png","banner":"https://api.mozambiquehe.re/assets/banners/wattson.jpg"}},"Fuse":{"data":[{"name":"BR Kills","value":183,"key":"specialEvent_kills","rank":{"rankPos":211491,"topPercent":31.45},"rankPlatformSpecific":{"rankPos":56215,"topPercent":42.17}},{"name":"BR Damage","value":81023,"key":"specialEvent_damage","rank":{"rankPos":214485,"topPercent":30.02},"rankPlatformSpecific":{"rankPos":60375,"topPercent":42.53}},{"name":"BR Wins","value":9,"key":"specialEvent_wins","rank":{"rankPos":145202,"topPercent":35.71},"rankPlatformSpecific":{"rankPos":36647,"topPercent":43.31}}],"ImgAssets":{"icon":"https://api.mozambiquehe.re/assets/icons/fuse.png","banner":"https://api.mozambiquehe.re/assets/banners/fuse.jpg"}},"Bangalore":{"data":[{"name":"BR Damage","value":50829,"key":"damage","rank":{"rankPos":586880,"topPercent":43.94},"rankPlatformSpecific":{"rankPos":100125,"topPercent":50.75}},{"name":"BR Kills","value":234,"key":"specialEvent_kills","rank":{"rankPos":473636,"topPercent":46.55},"rankPlatformSpecific":{"rankPos":72401,"topPercent":53.51}},{"name":"BR Damage","value":92333,"key":"specialEvent_damage","rank":{"rankPos":456426,"topPercent":44.07},"rankPlatformSpecific":{"rankPos":72784,"topPercent":52.37}},{"name":"BR Wins","value":17,"key":"specialEvent_wins","rank":{"rankPos":297697,"topPercent":39.98},"rankPlatformSpecific":{"rankPos":56102,"topPercent":44.03}},{"name":"BR Season 9 wins","value":1,"key":"wins_season_9","rank":{"rankPos":55044,"topPercent":40.6},"rankPlatformSpecific":{"rankPos":"NOT_CALCULATED_YET","topPercent":"NOT_CALCULATED_YET"}},{"name":"BR Season 9 kills","value":15,"key":"kills_season_9","rank":{"rankPos":88169,"topPercent":47.26},"rankPlatformSpecific":{"rankPos":"NOT_CALCULATED_YET","topPercent":"NOT_CALCULATED_YET"}},{"name":"BR Season 10 kills","value":10,"key":"kills_season_10","rank":{"rankPos":70952,"topPercent":51.09},"rankPlatformSpecific":{"rankPos":"NOT_CALCULATED_YET","topPercent":"NOT_CALCULATED_YET"}},{"name":"BR Season 10 wins","value":3,"key":"wins_season_10","rank":{"rankPos":24910,"topPercent":17.55},"rankPlatformSpecific":{"rankPos":"NOT_CALCULATED_YET","topPercent":"NOT_CALCULATED_YET"}}],"gameInfo":{"badges":[{"name":"Flawless Victory II","value":0},{"name":"Shot Caller","value":0}]},"ImgAssets":{"icon":"https://api.mozambiquehe.re/assets/icons/bangalore.png","banner":"https://api.mozambiquehe.re/assets/banners/bangalore.jpg"}},"Wraith":{"data":[{"name":"BR Kills","value":92,"key":"specialEvent_kills","rank":{"rankPos":1174048,"topPercent":81.64},"rankPlatformSpecific":{"rankPos":290466,"topPercent":86.15}},{"name":"BR Damage","value":30797,"key":"specialEvent_damage","rank":{"rankPos":1105071,"topPercent":85.21},"rankPlatformSpecific":{"rankPos":276738,"topPercent":89.79}},{"name":"BR Wins","value":5,"key":"specialEvent_wins","rank":{"rankPos":736459,"topPercent":80.44},"rankPlatformSpecific":{"rankPos":187463,"topPercent":81.86}}],"ImgAssets":{"icon":"https://api.mozambiquehe.re/assets/icons/wraith.png","banner":"https://api.mozambiquehe.re/assets/banners/wraith.jpg"}},"Octane":{"data":[{"name":"BR Kills","value":204,"key":"kills","rank":{"rankPos":2022498,"topPercent":46.12},"rankPlatformSpecific":{"rankPos":489730,"topPercent":50.2}},{"name":"BR Damage","value":79742,"key":"damage","rank":{"rankPos":1067338,"topPercent":69.71},"rankPlatformSpecific":{"rankPos":263194,"topPercent":74.79}},{"name":"BR Kills","value":217,"key":"specialEvent_kills","rank":{"rankPos":658288,"topPercent":79.4},"rankPlatformSpecific":{"rankPos":156530,"topPercent":81.29}},{"name":"BR Damage","value":83870,"key":"specialEvent_damage","rank":{"rankPos":514450,"topPercent":80.72},"rankPlatformSpecific":{"rankPos":133951,"topPercent":82.82}},{"name":"BR Season 9 wins","value":1,"key":"wins_season_9","rank":{"rankPos":127903,"topPercent":75.32},"rankPlatformSpecific":{"rankPos":"NOT_CALCULATED_YET","topPercent":"NOT_CALCULATED_YET"}},{"name":"BR Season 9 kills","value":24,"key":"kills_season_9","rank":{"rankPos":197469,"topPercent":79.87},"rankPlatformSpecific":{"rankPos":"NOT_CALCULATED_YET","topPercent":"NOT_CALCULATED_YET"}},{"name":"BR Season 10 kills","value":83,"key":"kills_season_10","rank":{"rankPos":107206,"topPercent":54.41},"rankPlatformSpecific":{"rankPos":"NOT_CALCULATED_YET","topPercent":"NOT_CALCULATED_YET"}},{"name":"BR Season 10 wins","value":8,"key":"wins_season_10","rank":{"rankPos":51590,"topPercent":30.37},"rankPlatformSpecific":{"rankPos":"NOT_CALCULATED_YET","topPercent":"NOT_CALCULATED_YET"}},{"name":"BR Season 12 wins","value":0,"key":"wins_season_12","rank":{"rankPos":76643,"topPercent":87.58},"rankPlatformSpecific":{"rankPos":14864,"topPercent":85.82}}],"gameInfo":{"badges":[{"name":"Squad Wipe","value":0},{"name":"Apex Octane","value":4}]},"ImgAssets":{"icon":"https://api.mozambiquehe.re/assets/icons/octane.png","banner":"https://api.mozambiquehe.re/assets/banners/octane.jpg"}},"Bloodhound":{"data":[{"name":"BR Kills","value":311,"key":"kills","rank":{"rankPos":1253732,"topPercent":24.18},"rankPlatformSpecific":{"rankPos":257637,"topPercent":21.37}},{"name":"BR Damage","value":125060,"key":"damage","rank":{"rankPos":812235,"topPercent":46.01},"rankPlatformSpecific":{"rankPos":173069,"topPercent":47.07}},{"name":"Eye: Enemies scanned","value":2345,"key":"enemies_scanned","rank":{"rankPos":504142,"topPercent":46.95},"rankPlatformSpecific":{"rankPos":110378,"topPercent":50.15}},{"name":"BR Kills","value":313,"key":"specialEvent_kills","rank":{"rankPos":725836,"topPercent":52.08},"rankPlatformSpecific":{"rankPos":144398,"topPercent":51.86}},{"name":"BR Season 9 wins","value":1,"key":"wins_season_9","rank":{"rankPos":134276,"topPercent":62.05},"rankPlatformSpecific":{"rankPos":"NOT_CALCULATED_YET","topPercent":"NOT_CALCULATED_YET"}},{"name":"BR Season 9 kills","value":31,"key":"kills_season_9","rank":{"rankPos":165639,"topPercent":55.35},"rankPlatformSpecific":{"rankPos":"NOT_CALCULATED_YET","topPercent":"NOT_CALCULATED_YET"}},{"name":"BR Season 10 kills","value":36,"key":"kills_season_10","rank":{"rankPos":100047,"topPercent":44.65},"rankPlatformSpecific":{"rankPos":14578,"topPercent":49.1}},{"name":"BR Season 10 wins","value":2,"key":"wins_season_10","rank":{"rankPos":87987,"topPercent":40.95},"rankPlatformSpecific":{"rankPos":12632,"topPercent":44.15}}],"gameInfo":{"badges":[{"name":"Hot Streak","value":0}]},"ImgAssets":{"icon":"https://api.mozambiquehe.re/assets/icons/bloodhound.png","banner":"https://api.mozambiquehe.re/assets/banners/bloodhound.jpg"}},"Caustic":{"data":[{"name":"BR Kills","value":109,"key":"specialEvent_kills","rank":{"rankPos":451606,"topPercent":64.11},"rankPlatformSpecific":{"rankPos":68724,"topPercent":66.58}},{"name":"BR Damage","value":48668,"key":"specialEvent_damage","rank":{"rankPos":417227,"topPercent":60.9},"rankPlatformSpecific":{"rankPos":66222,"topPercent":65.62}},{"name":"BR Wins","value":5,"key":"specialEvent_wins","rank":{"rankPos":220808,"topPercent":72.44},"rankPlatformSpecific":{"rankPos":39106,"topPercent":69.66}}],"gameInfo":{"badges":[{"name":"Squad Wipe","value":0}]},"ImgAssets":{"icon":"https://api.mozambiquehe.re/assets/icons/caustic.png","banner":"https://api.mozambiquehe.re/assets/banners/caustic.jpg"}},"Lifeline":{"data":[{"name":"BR Kills","value":475,"key":"kills","rank":{"rankPos":573363,"topPercent":13.19},"rankPlatformSpecific":{"rankPos":87786,"topPercent":9.44}},{"name":"BR Damage","value":184925,"key":"damage","rank":{"rankPos":378801,"topPercent":28.8},"rankPlatformSpecific":{"rankPos":57300,"topPercent":27.82}},{"name":"BR Season 10 kills","value":57,"key":"kills_season_10","rank":{"rankPos":12394,"topPercent":30.64},"rankPlatformSpecific":{"rankPos":"NOT_CALCULATED_YET","topPercent":"NOT_CALCULATED_YET"}},{"name":"BR Season 10 wins","value":4,"key":"wins_season_10","rank":{"rankPos":11973,"topPercent":27.29},"rankPlatformSpecific":{"rankPos":"NOT_CALCULATED_YET","topPercent":"NOT_CALCULATED_YET"}},{"name":"BR Season 13 wins","value":4,"key":"wins_season_13","rank":{"rankPos":8020,"topPercent":23.45},"rankPlatformSpecific":{"rankPos":3087,"topPercent":29.42}}],"gameInfo":{"badges":[{"name":"Squad Wipe","value":0}]},"ImgAssets":{"icon":"https://api.mozambiquehe.re/assets/icons/lifeline.png","banner":"https://api.mozambiquehe.re/assets/banners/lifeline.jpg"}},"Pathfinder":{"data":[{"name":"BR Kills","value":84,"key":"kills","rank":{"rankPos":2028567,"topPercent":49.26},"rankPlatformSpecific":{"rankPos":559485,"topPercent":53.97}},{"name":"BR SMG kills","value":20,"key":"smg_kills","rank":{"rankPos":13050,"topPercent":45.31},"rankPlatformSpecific":{"rankPos":"NOT_CALCULATED_YET","topPercent":"NOT_CALCULATED_YET"}},{"name":"Grapple: Travel distance","value":8109,"key":"grapple_travel_distance","rank":{"rankPos":553372,"topPercent":82.78},"rankPlatformSpecific":{"rankPos":"NOT_CALCULATED_YET","topPercent":"NOT_CALCULATED_YET"}},{"name":"BR Kills","value":101,"key":"specialEvent_kills","rank":{"rankPos":1038031,"topPercent":75.17},"rankPlatformSpecific":{"rankPos":303937,"topPercent":81.63}},{"name":"BR Damage","value":44499,"key":"specialEvent_damage","rank":{"rankPos":905740,"topPercent":72.36},"rankPlatformSpecific":{"rankPos":280208,"topPercent":80.9}},{"name":"BR Wins","value":6,"key":"specialEvent_wins","rank":{"rankPos":696422,"topPercent":69.47},"rankPlatformSpecific":{"rankPos":210939,"topPercent":75.73}}],"gameInfo":{"badges":[{"name":"Apex Pathfinder","value":0},{"name":"Shot Caller","value":0}]},"ImgAssets":{"icon":"https://api.mozambiquehe.re/assets/icons/pathfinder.png","banner":"https://api.mozambiquehe.re/assets/banners/pathfinder.jpg"}},"Loba":{"data":[{"name":"BR Kills","value":88,"key":"kills","rank":{"rankPos":987092,"topPercent":44.78},"rankPlatformSpecific":{"rankPos":194191,"topPercent":52.64}},{"name":"BR Kills","value":95,"key":"specialEvent_kills","rank":{"rankPos":528419,"topPercent":65.69},"rankPlatformSpecific":{"rankPos":97933,"topPercent":75.99}},{"name":"BR Damage","value":37058,"key":"specialEvent_damage","rank":{"rankPos":456663,"topPercent":69.11},"rankPlatformSpecific":{"rankPos":87830,"topPercent":80.21}},{"name":"BR Wins","value":5,"key":"specialEvent_wins","rank":{"rankPos":390100,"topPercent":68},"rankPlatformSpecific":{"rankPos":84685,"topPercent":75.37}},{"name":"BR Season 9 wins","value":1,"key":"wins_season_9","rank":{"rankPos":65426,"topPercent":61.6},"rankPlatformSpecific":{"rankPos":"NOT_CALCULATED_YET","topPercent":"NOT_CALCULATED_YET"}},{"name":"BR Season 9 kills","value":22,"key":"kills_season_9","rank":{"rankPos":87523,"topPercent":63.15},"rankPlatformSpecific":{"rankPos":"NOT_CALCULATED_YET","topPercent":"NOT_CALCULATED_YET"}}],"gameInfo":{"badges":[{"name":"Apex Loba","value":3}]},"ImgAssets":{"icon":"https://api.mozambiquehe.re/assets/icons/loba.png","banner":"https://api.mozambiquehe.re/assets/banners/loba.jpg"}},"Mirage":{"data":[{"name":"BR Kills","value":43,"key":"specialEvent_kills","rank":{"rankPos":658646,"topPercent":81.52},"rankPlatformSpecific":{"rankPos":83282,"topPercent":83.44}},{"name":"BR Damage","value":15769,"key":"specialEvent_damage","rank":{"rankPos":514511,"topPercent":85.2},"rankPlatformSpecific":{"rankPos":71071,"topPercent":86.34}},{"name":"BR Wins","value":1,"key":"specialEvent_wins","rank":{"rankPos":474602,"topPercent":87.65},"rankPlatformSpecific":{"rankPos":64319,"topPercent":87.58}}],"gameInfo":{"badges":[{"name":"Squad Wipe","value":0}]},"ImgAssets":{"icon":"https://api.mozambiquehe.re/assets/icons/mirage.png","banner":"https://api.mozambiquehe.re/assets/banners/mirage.jpg"}},"Rampart":{"data":[{"name":"BR Kills","value":94,"key":"kills","rank":{"rankPos":368336,"topPercent":26.97},"rankPlatformSpecific":{"rankPos":48918,"topPercent":34.59}},{"name":"Wall: Bullets amped","value":5100,"key":"bullets_amped","rank":{"rankPos":50093,"topPercent":44.73},"rankPlatformSpecific":{"rankPos":9460,"topPercent":58.94}},{"name":"BR Season 8 wins","value":2,"key":"wins_season_8","rank":{"rankPos":16145,"topPercent":31.77},"rankPlatformSpecific":{"rankPos":3323,"topPercent":59.17}}],"gameInfo":{"badges":[{"name":"Apex Rampart","value":0},{"name":"Rampart's Wrath","value":0}]},"ImgAssets":{"icon":"https://api.mozambiquehe.re/assets/icons/rampart.png","banner":"https://api.mozambiquehe.re/assets/banners/rampart.jpg"}},"Valkyrie":{"data":[{"name":"BR Kills","value":37,"key":"specialEvent_kills","rank":{"rankPos":952499,"topPercent":82.53},"rankPlatformSpecific":{"rankPos":184562,"topPercent":90.07}},{"name":"BR Damage","value":17386,"key":"specialEvent_damage","rank":{"rankPos":953635,"topPercent":79.72},"rankPlatformSpecific":{"rankPos":189350,"topPercent":88.81}},{"name":"BR Wins","value":1,"key":"specialEvent_wins","rank":{"rankPos":676606,"topPercent":88.85},"rankPlatformSpecific":{"rankPos":111943,"topPercent":91.38}}],"ImgAssets":{"icon":"https://api.mozambiquehe.re/assets/icons/valkyrie.png","banner":"https://api.mozambiquehe.re/assets/banners/valkyrie.jpg"}},"Seer":{"data":[{"name":"BR Kills","value":54,"key":"kills","rank":{"rankPos":661409,"topPercent":35.46},"rankPlatformSpecific":{"rankPos":167273,"topPercent":47.49}},{"name":"BR Kills","value":78,"key":"specialEvent_kills","rank":{"rankPos":343150,"topPercent":52.29},"rankPlatformSpecific":{"rankPos":86847,"topPercent":64.8}},{"name":"BR Damage","value":30843,"key":"specialEvent_damage","rank":{"rankPos":349690,"topPercent":51.16},"rankPlatformSpecific":{"rankPos":91023,"topPercent":65.32}},{"name":"BR Wins","value":5,"key":"specialEvent_wins","rank":{"rankPos":186850,"topPercent":47.17},"rankPlatformSpecific":{"rankPos":45740,"topPercent":57.85}},{"name":"BR Season 10 kills","value":36,"key":"kills_season_10","rank":{"rankPos":35333,"topPercent":58.99},"rankPlatformSpecific":{"rankPos":"NOT_CALCULATED_YET","topPercent":"NOT_CALCULATED_YET"}},{"name":"BR Season 10 wins","value":4,"key":"wins_season_10","rank":{"rankPos":30141,"topPercent":43.77},"rankPlatformSpecific":{"rankPos":"NOT_CALCULATED_YET","topPercent":"NOT_CALCULATED_YET"}}],"ImgAssets":{"icon":"https://api.mozambiquehe.re/assets/icons/seer.png","banner":"https://api.mozambiquehe.re/assets/banners/seer.jpg"}},"Ash":{"data":[{"name":"BR Kills","value":52,"key":"kills","rank":{"rankPos":791451,"topPercent":41.77},"rankPlatformSpecific":{"rankPos":"NOT_CALCULATED_YET","topPercent":"NOT_CALCULATED_YET"}},{"name":"Arc snare: Enemies tethered","value":27,"key":"tactical_enemy_tethered","rank":{"rankPos":191401,"topPercent":74.71},"rankPlatformSpecific":{"rankPos":"NOT_CALCULATED_YET","topPercent":"NOT_CALCULATED_YET"}},{"name":"BR Kills","value":64,"key":"specialEvent_kills","rank":{"rankPos":264378,"topPercent":66.56},"rankPlatformSpecific":{"rankPos":"NOT_CALCULATED_YET","topPercent":"NOT_CALCULATED_YET"}},{"name":"BR Damage","value":32398,"key":"specialEvent_damage","rank":{"rankPos":220754,"topPercent":62.15},"rankPlatformSpecific":{"rankPos":"NOT_CALCULATED_YET","topPercent":"NOT_CALCULATED_YET"}}],"gameInfo":{"badges":[{"name":"Ash's Wrath","value":0}]},"ImgAssets":{"icon":"https://api.mozambiquehe.re/assets/icons/ash.png","banner":"https://api.mozambiquehe.re/assets/banners/ash.jpg"}},"Mad Maggie":{"data":[{"name":"BR Kills","value":44,"key":"kills","rank":{"rankPos":50656,"topPercent":3.87},"rankPlatformSpecific":{"rankPos":17078,"topPercent":9.59}},{"name":"BR Kills","value":282,"key":"specialEvent_kills","rank":{"rankPos":28688,"topPercent":10.47},"rankPlatformSpecific":{"rankPos":9941,"topPercent":16.54}},{"name":"BR Damage","value":116944,"key":"specialEvent_damage","rank":{"rankPos":22250,"topPercent":10.24},"rankPlatformSpecific":{"rankPos":8137,"topPercent":16.43}},{"name":"BR Wins","value":18,"key":"specialEvent_wins","rank":{"rankPos":18054,"topPercent":7.82},"rankPlatformSpecific":{"rankPos":6602,"topPercent":12.74}}],"ImgAssets":{"icon":"https://api.mozambiquehe.re/assets/icons/mad maggie.png","banner":"https://api.mozambiquehe.re/assets/banners/mad maggie.jpg"}},"Newcastle":{"ImgAssets":{"icon":"https://api.mozambiquehe.re/assets/icons/newcastle.png","banner":"https://api.mozambiquehe.re/assets/banners/newcastle.jpg"}},"Vantage":{"ImgAssets":{"icon":"https://api.mozambiquehe.re/assets/icons/vantage.png","banner":"https://api.mozambiquehe.re/assets/banners/vantage.jpg"}}}},"mozambiquehere_internal":{"isNewToDB":false,"claimedBy":"1666732691","APIAccessType":"UNVERIFIED","ClusterID":"4","rate_limit":{"max_per_second":null,"current_req":"1"},"clusterSrv":"AUX1-CLUSTER"},"ALS":{"isALSDataEnabled":false},"total":{"damage":{"name":"BR Damage","value":1071546},"silenced_targets_kills":{"name":"Silence: Silenced knockdowns","value":131},"silenced_targets":{"name":"Silence: Enemies silenced","value":853},"specialEvent_kills":{"name":"BR Kills","value":3305},"kills_season_10":{"name":"BR Season 10 kills","value":380},"wins_season_10":{"name":"BR Season 10 wins","value":37},"kills":{"name":"BR Kills","value":2220},"passive_enemies_scanned":{"name":"Neurolink: Enemies scanned","value":63},"specialEvent_damage":{"name":"BR Damage","value":1059058},"specialEvent_wins":{"name":"BR Wins","value":160},"wins_season_8":{"name":"BR Season 8 wins","value":2},"revives":{"name":"BR Revives","value":130},"bombardment_kills":{"name":"Bombardment: Kills","value":14},"kills_season_7":{"name":"BR Season 7 kills","value":10},"wins_season_7":{"name":"BR Season 7 wins","value":2},"wins_season_9":{"name":"BR Season 9 wins","value":33},"kills_season_11":{"name":"BR Season 11 kills","value":174},"wins_season_11":{"name":"BR Season 11 wins","value":14},"wins_season_12":{"name":"BR Season 12 wins","value":8},"kills_season_12":{"name":"BR Season 12 kills","value":99},"winning_kills":{"name":"BR Winning kills","value":0},"marksman_kills":{"name":"BR Marksman kills","value":0},"kills_season_9":{"name":"BR Season 9 kills","value":92},"enemies_scanned":{"name":"Eye: Enemies scanned","value":2345},"wins_season_13":{"name":"BR Season 13 wins","value":4},"smg_kills":{"name":"BR SMG kills","value":20},"grapple_travel_distance":{"name":"Grapple: Travel distance","value":8109},"bullets_amped":{"name":"Wall: Bullets amped","value":5100},"tactical_enemy_tethered":{"name":"Arc snare: Enemies tethered","value":27},"kd":{"value":"-1","name":"KD"}}}